datasets/__init__.py
datasets/adult/__init__.py
datasets/adult/data/adult.data
datasets/adult/data/dtypes.json
datasets/socialdiagnosis/data/SocialDiagnosis2011.csv
datasets/winequality/__init__.py
datasets/winequality/data/dtypes.json
datasets/winequality/data/winequality-white.data
python_synthpop-0.1.2.dist-info/licenses/LICENSE
synthpop/__init__.py
synthpop/constants.py
synthpop/method/GC.py
synthpop/method/__init__.py
synthpop/method/cart.py
synthpop/method/helpers.py
synthpop/metrics/__init__.py
synthpop/metrics/diagnostic_report.py
synthpop/metrics/efficacy_metrics.py
synthpop/metrics/privacy_metrics.py
synthpop/metrics/single_columns_metrics.py
synthpop/processor/__init__.py
synthpop/processor/data_processor.py
synthpop/processor/missing_data_handler.py
synthpop/validator/__init__.py
synthpop/validator/validator.py
python_synthpop-0.1.2.dist-info/METADATA
python_synthpop-0.1.2.dist-info/WHEEL
python_synthpop-0.1.2.dist-info/top_level.txt
python_synthpop-0.1.2.dist-info/RECORD
