Metadata-Version: 2.4
Name: python-synthpop
Version: 0.1.2
Summary: Python implementation of the R package synthpop for generating synthetic data
Home-page: https://github.com/algorithm-audit/python-synthpop
Author: Algorithm Audit
Author-email: info@algorithmaudit.eu
License: EUROPEAN UNION PUBLIC LICENCE v. 1.2 EUPL © the European Union 2007, 2016
Requires-Python: >=3.7
License-File: LICENSE
Requires-Dist: numpy>=1.20.0
Requires-Dist: pandas>=1.3.0
Requires-Dist: scikit-learn>=1.0.0
Requires-Dist: copulas>=0.1.0
Provides-Extra: dev
Requires-Dist: pytest>=7.0.0; extra == "dev"
Dynamic: author-email
Dynamic: home-page
Dynamic: license-file
Dynamic: requires-python
